pyJMT/__init__.py
pyJMT/classes.py
pyJMT/drop_strategies.py
pyJMT/link.py
pyJMT/metrics.py
pyJMT/network.py
pyJMT/nodes.py
pyJMT/routing_strategies.py
pyJMT/scheduling_strategies.py
pyJMT/service_distributions.py
pyJMT-0.1.4.dist-info/LICENSE
pyJMT-0.1.4.dist-info/METADATA
pyJMT-0.1.4.dist-info/WHEEL
pyJMT-0.1.4.dist-info/top_level.txt
pyJMT-0.1.4.dist-info/RECORD
