Metadata-Version: 2.1
Name: pyJMT
Version: 0.1.4
Summary: A python wrapper for Java Modelling Tools (JMT)
Home-page: UNKNOWN
Author: James Stadler
Author-email: jws22@ic.ac.uk
License: BSD 3-Clause
Platform: UNKNOWN
Requires-Python: >=3.6
License-File: LICENSE
